MANIFEST.in
README.md
setup.py
data/GCF_000840245.1_ViralProj14204_genomic.fna
data/iontorrent_head400.fq
dnasnout_client.egg-info/PKG-INFO
dnasnout_client.egg-info/SOURCES.txt
dnasnout_client.egg-info/dependency_links.txt
dnasnout_client.egg-info/not-zip-safe
dnasnout_client.egg-info/requires.txt
dnasnout_client.egg-info/top_level.txt
src/__init__.py
src/align.py
src/console.py
src/match.py
src/test_align.py