Metadata-Version: 1.1
Name: dnasnout-client
Version: 0.3.0
Summary: DNASnout client
Home-page: http://www.cbs.dtu.dk/~laurent/dnasnout
Author: Laurent Gautier
Author-email: lgautier@gmail.com
License: This software is available under a dual license model: the AGPLv3 or a commercial license. If you need a commercial license, contact the author.
Platform: UNKNOWN
Classifier: Programming Language :: Python
Classifier: Programming Language :: Python :: 3
